README.rst
setup.py
aiourlstatus/__init__.py
aiourlstatus/app.py
aiourlstatus/checkurls.py
aiourlstatus.egg-info/PKG-INFO
aiourlstatus.egg-info/SOURCES.txt
aiourlstatus.egg-info/dependency_links.txt
aiourlstatus.egg-info/entry_points.txt
aiourlstatus.egg-info/not-zip-safe
aiourlstatus.egg-info/requires.txt
aiourlstatus.egg-info/top_level.txt