Metadata-Version: 1.1
Name: aiourlstatus
Version: 0.3.3
Summary: A tool to check links from a json / text file
Home-page: https://github.com/riverrun/aiourlstatus
Author: David Whitlock
Author-email: alovedalongthe@gmail.com
License: GPLv3
Platform: any
Classifier: Development Status :: 4 - Beta
Classifier: Environment :: Console
Classifier: Intended Audience :: Developers
Classifier: License :: OSI Approved :: GNU General Public License v3 (GPLv3)
Classifier: Operating System :: OS Independent
Classifier: Programming Language :: Python
Classifier: Programming Language :: Python :: 3.4
Classifier: Topic :: Internet :: WWW/HTTP :: Site Management :: Link Checking
